trajectopy_core/LICENSE
trajectopy_core/__init__.py
trajectopy_core/alignment/__init__.py
trajectopy_core/alignment/data.py
trajectopy_core/alignment/direct.py
trajectopy_core/alignment/egrad_interface.py
trajectopy_core/alignment/equations.py
trajectopy_core/alignment/estimation.py
trajectopy_core/alignment/parameters.py
trajectopy_core/alignment/result.py
trajectopy_core/alignment/utils.py
trajectopy_core/approximation/__init__.py
trajectopy_core/approximation/cubic_approximation.py
trajectopy_core/approximation/mls_approximation.py
trajectopy_core/approximation/rot_approximation.py
trajectopy_core/approximation/voxelizer.py
trajectopy_core/definitions.py
trajectopy_core/evaluation/__init__.py
trajectopy_core/evaluation/ate_result.py
trajectopy_core/evaluation/comparison.py
trajectopy_core/evaluation/deviations.py
trajectopy_core/evaluation/metrics.py
trajectopy_core/evaluation/rpe_result.py
trajectopy_core/evaluation/utils.py
trajectopy_core/input_output/__init__.py
trajectopy_core/input_output/header.py
trajectopy_core/input_output/rosbag.py
trajectopy_core/input_output/rosmsg.py
trajectopy_core/input_output/trajectory_io.py
trajectopy_core/input_output/utils.py
trajectopy_core/kml.py
trajectopy_core/matching.py
trajectopy_core/merging.py
trajectopy_core/plotting/__init__.py
trajectopy_core/plotting/mpl/__init__.py
trajectopy_core/plotting/mpl/alignment.py
trajectopy_core/plotting/mpl/default.mplstyle
trajectopy_core/plotting/mpl/results.py
trajectopy_core/plotting/mpl/trajectory.py
trajectopy_core/plotting/plotly/__init__.py
trajectopy_core/plotting/plotly/bar_plots.py
trajectopy_core/plotting/plotly/heatmaps.py
trajectopy_core/plotting/plotly/histograms.py
trajectopy_core/plotting/plotly/line_plots.py
trajectopy_core/plotting/plotly/multi_line_plots.py
trajectopy_core/plotting/plotly/scatter_plots.py
trajectopy_core/plotting/plotly/tables.py
trajectopy_core/plotting/utils.py
trajectopy_core/report/__init__.py
trajectopy_core/report/alignment.py
trajectopy_core-4.0.0.dist-info/LICENSE
trajectopy_core-4.0.0.dist-info/METADATA
trajectopy_core-4.0.0.dist-info/WHEEL
trajectopy_core-4.0.0.dist-info/RECORD
