Metadata-Version: 2.1
Name: trajectopy-core
Version: 4.0.0
Summary: Trajectory Evaluation in Python
Home-page: https://github.com/gereon-t/trajectopy-core
License: MIT
Keywords: trajectory,evaluation,alignment,similarity,leverarm,epsg,robotics
Author: Gereon Tombrink
Author-email: tombrink@igg.uni-bonn.de
Maintainer: Gereon Tombrink
Maintainer-email: tombrink@igg.uni-bonn.de
Requires-Python: >=3.9,<3.14
Classifier: License :: OSI Approved :: MIT License
Classifier: Programming Language :: Python :: 3
Classifier: Programming Language :: Python :: 3.9
Classifier: Programming Language :: Python :: 3.10
Classifier: Programming Language :: Python :: 3.11
Requires-Dist: autograd (>=1.6.2,<2.0.0)
Requires-Dist: jinja2 (>=3.1.3,<4.0.0)
Requires-Dist: matplotlib (>=3.8.2,<4.0.0)
Requires-Dist: networkx (>=3.2.1,<4.0.0)
Requires-Dist: numpy (>=1.26.1,<2.0.0)
Requires-Dist: pandas (>=2.2.0,<3.0.0)
Requires-Dist: plotly (>=5.18.0,<6.0.0)
Requires-Dist: pointset (>=0.1.5,<0.2.0)
Requires-Dist: rich (>=13.7.0,<14.0.0)
Requires-Dist: rosbags (>=0.9.20,<0.10.0)
Requires-Dist: scipy (>=1.12.0,<2.0.0)
Project-URL: Repository, https://github.com/gereon-t/trajectopy-core.git
